py3_infobip/__init__.py
py3_infobip/clients.py
py3_infobip/models.py
py3_infobip/utils/u_dict.py
py3_infobip-0.0.4.dist-info/LICENSE
py3_infobip-0.0.4.dist-info/WHEEL
py3_infobip-0.0.4.dist-info/METADATA
py3_infobip-0.0.4.dist-info/RECORD
